LICENSE
MANIFEST.in
README.md
setup.py
CTRNN/__init__.py
CTRNN/ctrnn.py
CTRNN.egg-info/PKG-INFO
CTRNN.egg-info/SOURCES.txt
CTRNN.egg-info/dependency_links.txt
CTRNN.egg-info/requires.txt
CTRNN.egg-info/top_level.txt