Metadata-Version: 1.0
Name: CTRNN
Version: 2.0
Summary: A package that implements Continuous Time Recurrent Neural Networks
Home-page: https://github.com/madvn/CTRNN
Author: Madhavun Candadai
Author-email: madvncv@gmail.com
License: MIT License
